simpy/__init__.py
simpy/_compat.py
simpy/_version.py
simpy/core.py
simpy/events.py
simpy/exceptions.py
simpy/rt.py
simpy/util.py
simpy/resources/__init__.py
simpy/resources/base.py
simpy/resources/container.py
simpy/resources/resource.py
simpy/resources/store.py
simpy_agents-1.0.0.dist-info/LICENSE
simpy_agents-1.0.0.dist-info/METADATA
simpy_agents-1.0.0.dist-info/WHEEL
simpy_agents-1.0.0.dist-info/top_level.txt
simpy_agents-1.0.0.dist-info/RECORD
