Metadata-Version: 2.1
Name: simpy-agents
Version: 1.0.0
Summary: An extension of SimPy for working with distinct agents.
Home-page: https://github.com/JakeNunemaker/simpy-agents
Author: Jake Nunemaker
Author-email: jake.d.nunemaker@gmail.com
License: MIT
Platform: UNKNOWN
Classifier: Programming Language :: Python :: 3
